dimg4md/__init__.py
dimg4md/cli.py
dimg4md/img4.py
py_dimg4md-0.2.1.dist-info/METADATA
py_dimg4md-0.2.1.dist-info/WHEEL
py_dimg4md-0.2.1.dist-info/entry_points.txt
py_dimg4md-0.2.1.dist-info/top_level.txt
py_dimg4md-0.2.1.dist-info/RECORD
