Metadata-Version: 2.4
Name: py-dimg4md
Version: 0.2.1
Requires-Dist: requests>=2.28.2
Requires-Dist: click>=8.0.0
Provides-Extra: picgo
Dynamic: provides-extra
Dynamic: requires-dist
